README.txt
plonetheme.relic-configure.zcml
setup.cfg
setup.py
docs/HISTORY.txt
docs/INSTALL.txt
docs/LICENSE.GPL
docs/LICENSE.txt
plonetheme/__init__.py
plonetheme.relic.egg-info/PKG-INFO
plonetheme.relic.egg-info/SOURCES.txt
plonetheme.relic.egg-info/dependency_links.txt
plonetheme.relic.egg-info/entry_points.txt
plonetheme.relic.egg-info/namespace_packages.txt
plonetheme.relic.egg-info/not-zip-safe
plonetheme.relic.egg-info/requires.txt
plonetheme.relic.egg-info/top_level.txt
plonetheme/relic/__init__.py
plonetheme/relic/configure.zcml
plonetheme/relic/profiles.zcml
plonetheme/relic/setuphandlers.py
plonetheme/relic/skins.zcml
plonetheme/relic/tests.py
plonetheme/relic/version.txt
plonetheme/relic/browser/__init__.py
plonetheme/relic/browser/configure.zcml
plonetheme/relic/browser/interfaces.py
plonetheme/relic/browser/viewlet.pt
plonetheme/relic/browser/viewlets.py
plonetheme/relic/browser/images/README.txt
plonetheme/relic/browser/images/header.jpg
plonetheme/relic/browser/stylesheets/README.txt
plonetheme/relic/browser/stylesheets/main.css
plonetheme/relic/browser/viewlets/relic_title.pt
plonetheme/relic/profiles/default/cssregistry.xml
plonetheme/relic/profiles/default/import_steps.xml
plonetheme/relic/profiles/default/jsregistry.xml
plonetheme/relic/profiles/default/plonetheme.relic_various.txt
plonetheme/relic/profiles/default/skins.xml
plonetheme/relic/profiles/default/viewlets.xml
plonetheme/relic/skins/plonetheme_relic_custom_images/CONTENT.txt
plonetheme/relic/skins/plonetheme_relic_custom_templates/CONTENT.txt
plonetheme/relic/skins/plonetheme_relic_styles/CONTENT.txt
plonetheme/relic/skins/plonetheme_relic_styles/base.css.dtml
plonetheme/relic/skins/plonetheme_relic_styles/base_properties.props
plonetheme/relic/skins/plonetheme_relic_styles/portlets.css.dtml
plonetheme/relic/skins/plonetheme_relic_styles/public.css.dtml
